humanoidagents/__init__.py
humanoidagents/customized_humanoid_agent.py
humanoidagents/generative_agent.py
humanoidagents/humanoid_agent.py
humanoidagents/llm.py
humanoidagents/location.py
humanoidagents/run_dashboard.py
humanoidagents/run_simulation.py
humanoidagents/utils.py
humanoidagents-0.1.2.dist-info/LICENSE
humanoidagents-0.1.2.dist-info/METADATA
humanoidagents-0.1.2.dist-info/WHEEL
humanoidagents-0.1.2.dist-info/top_level.txt
humanoidagents-0.1.2.dist-info/RECORD
