Metadata-Version: 2.1
Name: humanoidagents
Version: 0.1.2
Summary: Platform for Simulating Human-like Generative Agents
Home-page: https://github.com/HumanoidAgents/HumanoidAgents
Author: Humanoid Agents
Author-email: humanoidagents@gmail.com
Requires-Python: >=3.7
License-File: LICENSE
Requires-Dist: openai (>=0.27.2)
Requires-Dist: numpy (>=1.23.5)
Requires-Dist: scikit-learn (>=1.2.1)
Requires-Dist: dash (>=2.11.1)
Requires-Dist: dash-daq (>=0.5.0)
Requires-Dist: dash-bootstrap-components (>=1.4.2)
Requires-Dist: PyYAML (>=6.0)
Requires-Dist: pandas (>=2.0.2)
Requires-Dist: plotly (>=5.15.0)
